CommonKeywords/CommonKeywordsAPI.robot
CommonKeywords/CommonKeywordsDynamodb.robot
CommonKeywords/CommonKeywordsRDS.robot
CommonKeywords/CommonKeywordsUI.robot
CommonKeywords/DateTime1.py
CommonKeywords/__init__.py
CommonKeywords/data_type_conversion.py
CommonKeywords/dbKeywords.py
Test/Example1.robot
Test/__init__.py
robotframework_commonKeywrds-0.0.1.dist-info/METADATA
robotframework_commonKeywrds-0.0.1.dist-info/WHEEL
robotframework_commonKeywrds-0.0.1.dist-info/top_level.txt
robotframework_commonKeywrds-0.0.1.dist-info/RECORD
