Metadata-Version: 2.1
Name: robotframework-commonKeywrds
Version: 0.0.1
Summary: robotframework_commonKeywrds
Home-page: UNKNOWN
Author: Ritika
Author-email: ritika.kumar90@gmail.com
License: UNKNOWN
Keywords: arithmetic,CommonKeywords,mathematics,python tutorial,Ritika kumar
Platform: UNKNOWN
Classifier: Development Status :: 1 - Planning
Classifier: Intended Audience :: Developers
Classifier: Programming Language :: Python :: 3
Classifier: Operating System :: Unix
Classifier: Operating System :: MacOS :: MacOS X
Classifier: Operating System :: Microsoft :: Windows
Requires-Dist: robotframework
Requires-Dist: robotframework-seleniumlibrary
Requires-Dist: robotframework-requests
Requires-Dist: robotframework-jsonlibrary
Requires-Dist: robotframework-seleniumscreenshots
Requires-Dist: robotframework-datetime-tz
Requires-Dist: robotframework-pabot
Requires-Dist: robotframework-csvlib
Requires-Dist: robotframework-databaselibrary
Requires-Dist: boto3
